Cut4Url/Cut4Url.py
Cut4Url/__init__.py
Cut4Url-2.1.dist-info/LICENSE.txt
Cut4Url-2.1.dist-info/METADATA
Cut4Url-2.1.dist-info/WHEEL
Cut4Url-2.1.dist-info/top_level.txt
Cut4Url-2.1.dist-info/RECORD
