Metadata-Version: 2.1
Name: Cut4Url
Version: 2.1
Summary: A simple library for shortening links
Classifier: Programming Language :: Python :: 3
Classifier: License :: OSI Approved :: MIT License
Classifier: Operating System :: OS Independent
Requires-Python: >=3.6
License-File: LICENSE.txt
